workflow/__init__.py
workflow/setup.py
workflow/workflow_details.py
workflow_package-3.1.1.dist-info/METADATA
workflow_package-3.1.1.dist-info/WHEEL
workflow_package-3.1.1.dist-info/top_level.txt
workflow_package-3.1.1.dist-info/RECORD
