Metadata-Version: 2.1
Name: workflow-package
Version: 3.1.1
Summary: A package for workflow details
Home-page: UNKNOWN
Author: Ninja Coder
Author-email: ninjacoder@gmail.com
License: UNKNOWN
Platform: UNKNOWN
Classifier: Development Status :: 5 - Production/Stable
